Metadata-Version: 2.1
Name: semp
Version: 1.0
Summary: Selenium made simple(just a bit)!
Home-page: http://github.com/dogonso/semp
Author: Dogukan Meral
Author-email: dogukan.meral@yahoo.com
License: MIT
Keywords: selenium python library manipulate website geckodriver firefox automation webbot bot dogukan meral
Platform: UNKNOWN
Classifier: License :: OSI Approved :: MIT License
Classifier: Operating System :: Microsoft :: Windows
Classifier: Operating System :: POSIX :: Linux
Classifier: Operating System :: MacOS
Classifier: Programming Language :: Python :: 3.8
Classifier: Topic :: Internet
Classifier: Topic :: Software Development :: Libraries
Classifier: Topic :: Internet :: WWW/HTTP :: Site Management
Classifier: Topic :: Utilities
